{"schema_version":"cfcode.hyde.v1","repo_slug":"lumae-fresh-filtered-smoke-10","source_chunk_identity":"97930dbeb0c265e4a7629b32e7fbf17b","content_hash":"bc24036e6330e4153785c996e20e440290564124b66363a7a9969def815a830f","hyde_version":"template-hyde-v1","hyde_model":"deterministic-template","hyde_key":"71ed7c756acfea8750c37ce0b48d3a5101150460f18402ae5b6cb9431b9713b6","questions":["Where is purchase_price not round assets borrowers_list down_percent handled in 1003ingest/parse_1003.py?","What code around lines 601-720 implements purchase_price?","How does 1003ingest/parse_1003.py use purchase_price, not, round?"],"embedding_agnostic":true}
